pyppet/__init__.py
pyppet/format.py
pyppet/rerun.py
pyppet/urdf.py
pyppet/examples/README.md
pyppet/examples/__init__.py
pyppet/examples/example_mesh.stl
pyppet/examples/example_model.py
pyppet-1.0.2.dist-info/METADATA
pyppet-1.0.2.dist-info/WHEEL
pyppet-1.0.2.dist-info/licenses/LICENSE
pyppet-1.0.2.dist-info/RECORD
